plugged/__init__.py
plugged/entry.py
plugged/imp.py
plugged/mixin.py
plugged-0.1.1.dist-info/LICENSE
plugged-0.1.1.dist-info/METADATA
plugged-0.1.1.dist-info/WHEEL
plugged-0.1.1.dist-info/top_level.txt
plugged-0.1.1.dist-info/zip-safe
plugged-0.1.1.dist-info/RECORD
