Metadata-Version: 2.1
Name: plugged
Version: 0.1.1
Summary: A lightweight arbitrary plugin system based off SourceFileLoaderc
Home-page: UNKNOWN
Author: UNKNOWN
Author-email: UNKNOWN
License: MIT
Platform: UNKNOWN
